PySoAL/Solver.py
PySoAL/__init__.py
PySoAL/gurobi.py
PySoAL-0.2.10.dist-info/LICENSE
PySoAL-0.2.10.dist-info/METADATA
PySoAL-0.2.10.dist-info/WHEEL
PySoAL-0.2.10.dist-info/top_level.txt
PySoAL-0.2.10.dist-info/RECORD
