Metadata-Version: 2.1
Name: PySoAL
Version: 0.2.10
Summary: Solver abstraction layer for power system optimization
Author: Thomas Offergeld
Author-email: t.offergeld@iaew.rwth-aachen.de
Classifier: Programming Language :: Python
Classifier: Programming Language :: Python :: 3
License-File: LICENSE
Requires-Dist: numpy
Requires-Dist: gurobipy
Provides-Extra: test
Requires-Dist: pytest ; extra == 'test'
Requires-Dist: pytest-xdist ; extra == 'test'
